{"cameraMode":{"drawMode":0,"name":"Shaded","section":"Shading Mode"},"sceneLighting":true,"audioPlay":false,"sceneViewState":{"m_AlwaysRefresh":false,"showFog":true,"showSkybox":true,"showFlares":true,"showImageEffects":true,"showParticleSystems":true,"showVisualEffectGraphs":true,"m_FxEnabled":true},"in2DMode":false,"pivot":{"x":0.739533543586731,"y":5.086042881011963,"z":-0.7139551043510437},"rotation":{"x":0.0790080651640892,"y":-0.9188060760498047,"z":0.23834365606307984,"w":0.3045925199985504},"size":3.9140098094940187,"orthographic":false}